{"@timestamp":"2023-11-27T01:48:27.380Z","log.level":"DEBUG","message":"Application availability state ReadinessState changed from ACCEPTING_TRAFFIC to REFUSING_TRAFFIC","ecs.version": "1.2.0","service.name":"log-structura","event.dataset":"log-structura","process.thread.name":"SpringApplicationShutdownHook","log.logger":"org.springframework.boot.availability.ApplicationAvailabilityBean"}
{"@timestamp":"2023-11-27T01:48:27.394Z","log.level":"DEBUG","message":"Closing org.springframework.boot.web.servlet.context.AnnotationConfigServletWebServerApplicationContext@20ce78ec, started on Sun Nov 26 23:37:23 UTC 2023","ecs.version": "1.2.0","service.name":"log-structura","event.dataset":"log-structura","process.thread.name":"SpringApplicationShutdownHook","log.logger":"org.springframework.boot.web.servlet.context.AnnotationConfigServletWebServerApplicationContext"}
{"@timestamp":"2023-11-27T01:48:27.411Z","log.level":"DEBUG","message":"Stopping beans in phase 2147482623","ecs.version": "1.2.0","service.name":"log-structura","event.dataset":"log-structura","process.thread.name":"SpringApplicationShutdownHook","log.logger":"org.springframework.context.support.DefaultLifecycleProcessor"}
{"@timestamp":"2023-11-27T01:48:27.414Z","log.level": "INFO","message":"Commencing graceful shutdown. Waiting for active requests to complete","ecs.version": "1.2.0","service.name":"log-structura","event.dataset":"log-structura","process.thread.name":"SpringApplicationShutdownHook","log.logger":"org.springframework.boot.web.embedded.tomcat.GracefulShutdown"}
{"@timestamp":"2023-11-27T01:48:27.426Z","log.level": "INFO","message":"Graceful shutdown complete","ecs.version": "1.2.0","service.name":"log-structura","event.dataset":"log-structura","process.thread.name":"tomcat-shutdown","log.logger":"org.springframework.boot.web.embedded.tomcat.GracefulShutdown"}
{"@timestamp":"2023-11-27T01:48:27.427Z","log.level":"DEBUG","message":"Stopping beans in phase 2147481599","ecs.version": "1.2.0","service.name":"log-structura","event.dataset":"log-structura","process.thread.name":"SpringApplicationShutdownHook","log.logger":"org.springframework.context.support.DefaultLifecycleProcessor"}
{"@timestamp":"2023-11-27T01:48:27.427Z","log.level":"DEBUG","message":"Bean 'webServerGracefulShutdown' completed its stop procedure","ecs.version": "1.2.0","service.name":"log-structura","event.dataset":"log-structura","process.thread.name":"tomcat-shutdown","log.logger":"org.springframework.context.support.DefaultLifecycleProcessor"}
{"@timestamp":"2023-11-27T01:48:27.445Z","log.level":"DEBUG","message":"Bean 'webServerStartStop' completed its stop procedure","ecs.version": "1.2.0","service.name":"log-structura","event.dataset":"log-structura","process.thread.name":"SpringApplicationShutdownHook","log.logger":"org.springframework.context.support.DefaultLifecycleProcessor"}
{"@timestamp":"2023-11-27T01:48:27.445Z","log.level":"DEBUG","message":"Stopping beans in phase -2147483647","ecs.version": "1.2.0","service.name":"log-structura","event.dataset":"log-structura","process.thread.name":"SpringApplicationShutdownHook","log.logger":"org.springframework.context.support.DefaultLifecycleProcessor"}
{"@timestamp":"2023-11-27T01:48:27.446Z","log.level":"DEBUG","message":"Bean 'springBootLoggingLifecycle' completed its stop procedure","ecs.version": "1.2.0","service.name":"log-structura","event.dataset":"log-structura","process.thread.name":"SpringApplicationShutdownHook","log.logger":"org.springframework.context.support.DefaultLifecycleProcessor"}
{"@timestamp":"2023-11-27T01:48:27.447Z","log.level":"DEBUG","message":"Shutting down ExecutorService 'applicationTaskExecutor'","ecs.version": "1.2.0","service.name":"log-structura","event.dataset":"log-structura","process.thread.name":"SpringApplicationShutdownHook","log.logger":"org.springframework.scheduling.concurrent.ThreadPoolTaskExecutor"}
